{
"ordini": [

    { "order_id": 0001,
      "items": [243, 567, 111],
      "missing_items": false,
	  "price": 10.99,
	  "driver":{
		  "driver_id":1156,
		  "driver_rating": 8.9}
	},
	{ "order_id": 0002,
      "items": [932, 702, 111],
      "missing_items": false,
	  "price": 23.99,
	  "driver":{
		  "driver_id":1111,
		  "driver_rating": 9.9}
	},
	{ "order_id": 0003,
      "items": [567, 111],
      "missing_items": false,
	  "price": 205.99,
	  "driver":{
		  "driver_id":1100,
		  "driver_rating": 7.8}
	},
	{ "order_id": 0004,
      "items": [243, 999, 754, 111],
      "missing_items":true,
	  "price": 1056.99,
	  "driver":{
		  "driver_id":1122,
		  "driver_rating": 3.9}
	},
	{ "order_id": 0005,
      "items": [333, 111],
      "missing_items": false,
	  "price": 111.99,
	  "driver":{
		  "driver_id":1156,
		  "driver_rating": 8.9}
	},
	{ "order_id": 0006,
      "items": [293, 123, 111],
      "missing_items": false,
	  "price": 305.99,
	  "driver":{
		  "driver_id":1100,
		  "drivet_rating": 7.8}
	},
	{ "order_id": 0007,
      "items": [243, 567, 111],
      "missing_items": false,
	  "price": 26.99,
	  "driver":{
		  "driver_id":1111,
		  "driver_rating": 9.9}
	},
	{ "order_id": 0008,
      "items": [243, 595, 111],
      "missing_items": false,
	  "price": 15.99,
	  "driver":{
		  "driver_id":1113,
		  "driver_rating": 7.1}
	},
	{ "order_id": 0009,
      "items": [567, 111],
      "missing_items": false,
	  "price": 10.99,
	  "driver":{
		  "driver_id":1156,
		  "driver_rating": 8.9}
	},
	{ "order_id": 0010,
      "items": [823, 243, 567, 111],
      "missing_items": false,
	  "price": 56.99,
	  "driver":{
		  "driver_id":1119,
		  "driver_rating": 8.1}
	}
	]
	
}